README
setup.py
consistent_memcache/__init__.py
consistent_memcache/s3/__init__.py
consistent_memcache/s3/markhash.py
python_consistent_memcached.egg-info/PKG-INFO
python_consistent_memcached.egg-info/SOURCES.txt
python_consistent_memcached.egg-info/dependency_links.txt
python_consistent_memcached.egg-info/requires.txt
python_consistent_memcached.egg-info/top_level.txt
python_consistent_memcached.egg-info/zip-safe
scripts/ec2_markhash