Metadata-Version: 1.0
Name: python-consistent-memcached
Version: 0.0.1
Summary: python-memcached with consistent hashing
Home-page: https://github.com/wnyc/python_consistent_memcached
Author: Adam DePrince
Author-email: adeprince@nypublicradio.org
License: GPL
Platform: UNKNOWN
